ghsearch/__init__.py
ghsearch/cli.py
ghsearch/client.py
ghsearch/filters.py
ghsearch/gh_search.py
ghsearch/main.py
ghsearch/output.py
ghsearch/terminal.py
gh_search-0.9.1.dist-info/METADATA
gh_search-0.9.1.dist-info/WHEEL
gh_search-0.9.1.dist-info/entry_points.txt
gh_search-0.9.1.dist-info/top_level.txt
gh_search-0.9.1.dist-info/RECORD
