Metadata-Version: 2.1
Name: gh-search
Version: 0.9.1
Summary: Github search from the cli
Home-page: https://github.com/janeklb/gh-search
Author: Janek Lasocki-Biczysko
Classifier: Programming Language :: Python :: 3.12
Requires-Python: >=3.12
Requires-Dist: click~=8.1.7
Requires-Dist: click-config-file~=0.6.0
Requires-Dist: PyGithub~=2.3.0
Requires-Dist: ruamel.yaml~=0.18.6
Provides-Extra: dev
Requires-Dist: black~=24.8.0; extra == "dev"
Requires-Dist: coverage~=7.6.0; extra == "dev"
Requires-Dist: flake8~=7.1.0; extra == "dev"
Requires-Dist: isort~=5.13.2; extra == "dev"
Requires-Dist: mypy~=1.11.1; extra == "dev"
Requires-Dist: pip-tools~=7.4.1; extra == "dev"
Requires-Dist: pytest-mock~=3.14.0; extra == "dev"
Requires-Dist: pytest~=8.3.2; extra == "dev"
